Workbook

Sheet Orders
A1: Region | B1: State | C1: City | D1: Account | E1: Order ID | F1: Order Date | G1: Ship Date | H1: Days to Ship | I1: Sales Rep | J1: Channel | K1: Category | L1: Product | M1: SKU | N1: Qty | O1: Unit Price | P1: Extended | Q1: Discount % | R1: Discount Amt | S1: Net | T1: Sales Tax | U1: Total | V1: Shipping | W1: Landed Total | X1: Status | Y1: Notes
A2: Midwest | B2: Kentucky | C2: Louisville | D2: Ridge Distributors | E2: 41000 | F2: 46232 | G2: 46238 | H2: =IF(G2="","",G2-F2) -> 6 | I2: M. Okafor | J2: Online | K2: Hand Tools | L2: Torpedo Level 9 in | M2: HT-0900 | N2: 50 | O2: 14.25 | P2: =N2*O2 -> 712.5 | Q2: 0 | R2: =ROUND(P2*Q2,2) -> 0 | S2: =P2-R2 -> 712.5 | T2: =ROUND(S2*Assumptions!$B$2,2) -> 42.75 | U2: =S2+T2 -> 755.25 | V2: 6.12 | W2: =U2+V2 -> 761.37 | X2: Shipped
A3: Midwest | B3: Kentucky | C3: Louisville | D3: Ridge Distributors | E3: 41004 | F3: 46174 | H3: =IF(G3="","",G3-F3) | I3: M. Okafor | J3: Distributor | K3: Safety | L3: Safety Glasses, Clear (12) | M3: SF-0012 | N3: 50 | O3: 27.6 | P3: =N3*O3 -> 1380 | Q3: 0.1 | R3: =ROUND(P3*Q3,2) -> 138 | S3: =P3-R3 -> 1242 | T3: =ROUND(S3*Assumptions!$B$2,2) -> 74.52 | U3: =S3+T3 -> 1316.52 | V3: 27.9 | W3: =U3+V3 -> 1344.42 | X3: Backordered
A4: Midwest | B4: Kentucky | C4: Louisville | D4: Granite Fabrication | E4: 41008 | F4: 46029 | G4: 46030 | H4: =IF(G4="","",G4-F4) -> 1 | I4: A. Reyes | J4: Direct | K4: Electrical | L4: Duplex Outlet 15A (10) | M4: EL-1510 | N4: 10 | O4: 13.4 | P4: =N4*O4 -> 134 | Q4: 0.15 | R4: =ROUND(P4*Q4,2) -> 20.1 | S4: =P4-R4 -> 113.9 | T4: =ROUND(S4*Assumptions!$B$2,2) -> 6.83 | U4: =S4+T4 -> 120.73 | V4: 25.42 | W4: =U4+V4 -> 146.15 | X4: Delivered | Y4: Damaged in transit; replaced
A5: Midwest | B5: Kentucky | C5: Louisville | D5: Granite Fabrication | E5: 41011 | F5: 46077 | H5: =IF(G5="","",G5-F5) | I5: M. Okafor | J5: Online | K5: Fasteners | L5: Deck Screw #10 x 3 (5 lb) | M5: FAS-1003 | N5: 50 | O5: 31.9 | P5: =N5*O5 -> 1595 | Q5: 0 | R5: =ROUND(P5*Q5,2) -> 0 | S5: =P5-R5 -> 1595 | T5: =ROUND(S5*Assumptions!$B$2,2) -> 95.7 | U5: =S5+T5 -> 1690.7 | V5: 0 | W5: =U5+V5 -> 1690.7 | X5: Open | Y5: New account
A6: Midwest | B6: Kentucky | C6: Louisville | D6: Granite Fabrication | E6: 41013 | F6: 46257 | G6: 46262 | H6: =IF(G6="","",G6-F6) -> 5 | I6: M. Okafor | J6: Distributor | K6: Fasteners | L6: Deck Screw #10 x 3 (5 lb) | M6: FAS-1003 | N6: 10 | O6: 31.9 | P6: =N6*O6 -> 319 | Q6: 0 | R6: =ROUND(P6*Q6,2) -> 0 | S6: =P6-R6 -> 319 | T6: =ROUND(S6*Assumptions!$B$2,2) -> 19.14 | U6: =S6+T6 -> 338.14 | V6: 38.82 | W6: =U6+V6 -> 376.96 | X6: Delivered
A7: Midwest | B7: Kentucky | C7: Louisville | D7: Anchor Outfitters | E7: 41019 | F7: 46045 | G7: 46049 | H7: =IF(G7="","",G7-F7) -> 4 | I7: M. Okafor | J7: Online | K7: Fasteners | L7: Lag Screw 3/8 x 4 (50) | M7: FAS-3804 | N7: 6 | O7: 22.75 | P7: =N7*O7 -> 136.5 | Q7: 0.05 | R7: =ROUND(P7*Q7,2) -> 6.83 | S7: =P7-R7 -> 129.67 | T7: =ROUND(S7*Assumptions!$B$2,2) -> 7.78 | U7: =S7+T7 -> 137.45 | V7: 1 | W7: =U7+V7 -> 138.45 | X7: Delivered | Y7: New account
A8: Midwest | B8: Kentucky | C8: Louisville | D8: Anchor Outfitters | E8: 41023 | F8: 46140 | G8: 46149 | H8: =IF(G8="","",G8-F8) -> 9 | I8: A. Reyes | J8: Direct | K8: Electrical | L8: LED Shop Light 4 ft | M8: EL-0400 | N8: 15 | O8: 42 | P8: =N8*O8 -> 630 | Q8: 0 | R8: =ROUND(P8*Q8,2) -> 0 | S8: =P8-R8 -> 630 | T8: =ROUND(S8*Assumptions!$B$2,2) -> 37.8 | U8: =S8+T8 -> 667.8 | V8: 31.69 | W8: =U8+V8 -> 699.49 | X8: Delivered | Y8: Reorder of prior PO
A9: Midwest | B9: Kentucky | C9: Louisville | D9: Anchor Outfitters | E9: 41026 | F9: 46153 | G9: 46162 | H9: =IF(G9="","",G9-F9) -> 9 | I9: M. Okafor | J9: Distributor | K9: Power Tools | L9: Angle Grinder 4-1/2 in | M9: PT-4500 | N9: 8 | O9: 64.5 | P9: =N9*O9 -> 516 | Q9: 0.15 | R9: =ROUND(P9*Q9,2) -> 77.4 | S9: =P9-R9 -> 438.6 | T9: =ROUND(S9*Assumptions!$B$2,2) -> 26.32 | U9: =S9+T9 -> 464.92 | V9: 39.79 | W9: =U9+V9 -> 504.71 | X9: Delivered | Y9: Damaged in transit; replaced
A10: Midwest | B10: Kentucky | C10: Louisville | D10: Anchor Outfitters | E10: 41027 | F10: 46235 | H10: =IF(G10="","",G10-F10) | I10: A. Reyes | J10: Distributor | K10: Hand Tools | L10: Adjustable Wrench 10 in | M10: HT-1000 | N10: 2 | O10: 19.5 | P10: =N10*O10 -> 39 | Q10: 0.1 | R10: =ROUND(P10*Q10,2) -> 3.9 | S10: =P10-R10 -> 35.1 | T10: =ROUND(S10*Assumptions!$B$2,2) -> 2.11 | U10: =S10+T10 -> 37.21 | V10: 9.02 | W10: =U10+V10 -> 46.23 | X10: Backordered
A11: Midwest | B11: Kentucky | C11: Louisville | D11: Anchor Outfitters | E11: 41032 | F11: 46024 | G11: 46030 | H11: =IF(G11="","",G11-F11) -> 6 | I11: M. Okafor | J11: Distributor | K11: Hand Tools | L11: Adjustable Wrench 10 in | M11: HT-1000 | N11: 10 | O11: 19.5 | P11: =N11*O11 -> 195 | Q11: 0 | R11: =ROUND(P11*Q11,2) -> 0 | S11: =P11-R11 -> 195 | T11: =ROUND(S11*Assumptions!$B$2,2) -> 11.7 | U11: =S11+T11 -> 206.7 | V11: 5.33 | W11: =U11+V11 -> 212.03 | X11: Delivered | Y11: Customer pickup
A12: Midwest | B12: Kentucky | C12: Louisville | D12: Anchor Outfitters | E12: 41033 | F12: 46202 | H12: =IF(G12="","",G12-F12) | I12: M. Okafor | J12: Distributor | K12: Hand Tools | L12: Torpedo Level 9 in | M12: HT-0900 | N12: 4 | O12: 14.25 | P12: =N12*O12 -> 57 | Q12: 0 | R12: =ROUND(P12*Q12,2) -> 0 | S12: =P12-R12 -> 57 | T12: =ROUND(S12*Assumptions!$B$2,2) -> 3.42 | U12: =S12+T12 -> 60.42 | V12: 0 | W12: =U12+V12 -> 60.42 | X12: Open | Y12: New account
A13: Midwest | B13: Kentucky | C13: Lexington | D13: Beacon Industrial | E13: 41035 | F13: 46254 | G13: 46259 | H13: =IF(G13="","",G13-F13) -> 5 | I13: A. Reyes | J13: Distributor | K13: Fasteners | L13: Lag Screw 3/8 x 4 (50) | M13: FAS-3804 | N13: 20 | O13: 22.75 | P13: =N13*O13 -> 455 | Q13: 0.15 | R13: =ROUND(P13*Q13,2) -> 68.25 | S13: =P13-R13 -> 386.75 | T13: =ROUND(S13*Assumptions!$B$2,2) -> 23.21 | U13: =S13+T13 -> 409.96 | V13: 22.32 | W13: =U13+V13 -> 432.28 | X13: Delivered | Y13: Rush order
A14: Midwest | B14: Kentucky | C14: Lexington | D14: Beacon Industrial | E14: 41038 | F14: 46037 | H14: =IF(G14="","",G14-F14) | I14: M. Okafor | J14: Online | K14: Power Tools | L14: Angle Grinder 4-1/2 in | M14: PT-4500 | N14: 40 | O14: 64.5 | P14: =N14*O14 -> 2580 | Q14: 0 | R14: =ROUND(P14*Q14,2) -> 0 | S14: =P14-R14 -> 2580 | T14: =ROUND(S14*Assumptions!$B$2,2) -> 154.8 | U14: =S14+T14 -> 2734.8 | V14: 0 | W14: =U14+V14 -> 2734.8 | X14: Open | Y14: New account
A15: Midwest | B15: Kentucky | C15: Lexington | D15: Beacon Industrial | E15: 41041 | F15: 46237 | G15: 46239 | H15: =IF(G15="","",G15-F15) -> 2 | I15: M. Okafor | J15: Online | K15: Electrical | L15: Romex 12/2 NM-B 250 ft | M15: EL-1225 | N15: 5 | O15: 118 | P15: =N15*O15 -> 590 | Q15: 0 | R15: =ROUND(P15*Q15,2) -> 0 | S15: =P15-R15 -> 590 | T15: =ROUND(S15*Assumptions!$B$2,2) -> 35.4 | U15: =S15+T15 -> 625.4 | V15: 22.86 | W15: =U15+V15 -> 648.26 | X15: Delivered
A16: Midwest | B16: Kentucky | C16: Lexington | D16: Beacon Industrial | E16: 41047 | F16: 46118 | G16: 46120 | H16: =IF(G16="","",G16-F16) -> 2 | I16: M. Okafor | J16: Online | K16: Electrical | L16: LED Shop Light 4 ft | M16: EL-0400 | N16: 24 | O16: 42 | P16: =N16*O16 -> 1008 | Q16: 0.1 | R16: =ROUND(P16*Q16,2) -> 100.8 | S16: =P16-R16 -> 907.2 | T16: =ROUND(S16*Assumptions!$B$2,2) -> 54.43 | U16: =S16+T16 -> 961.63 | V16: 11.44 | W16: =U16+V16 -> 973.07 | X16: Delivered
A17: Midwest | B17: Kentucky | C17: Lexington | D17: Beacon Industrial | E17: 41050 | F17: 46178 | G17: 46183 | H17: =IF(G17="","",G17-F17) -> 5 | I17: M. Okafor | J17: Distributor | K17: Electrical | L17: LED Shop Light 4 ft | M17: EL-0400 | N17: 30 | O17: 42 | P17: =N17*O17 -> 1260 | Q17: 0.05 | R17: =ROUND(P17*Q17,2) -> 63 | S17: =P17-R17 -> 1197 | T17: =ROUND(S17*Assumptions!$B$2,2) -> 71.82 | U17: =S17+T17 -> 1268.82 | V17: 17.31 | W17: =U17+V17 -> 1286.13 | X17: Delivered
A18: Midwest | B18: Kentucky | C18: Lexington | D18: Beacon Industrial | E18: 41054 | F18: 46131 | G18: 46140 | H18: =IF(G18="","",G18-F18) -> 9 | I18: A. Reyes | J18: Distributor | K18: Electrical | L18: LED Shop Light 4 ft | M18: EL-0400 | N18: 8 | O18: 42 | P18: =N18*O18 -> 336 | Q18: 0.1 | R18: =ROUND(P18*Q18,2) -> 33.6 | S18: =P18-R18 -> 302.4 | T18: =ROUND(S18*Assumptions!$B$2,2) -> 18.14 | U18: =S18+T18 -> 320.54 | V18: 33.7 | W18: =U18+V18 -> 354.24 | X18: Delivered
A19: Midwest | B19: Kentucky | C19: Lexington | D19: Oak Outfitters | E19: 41057 | F19: 46198 | G19: 46200 | H19: =IF(G19="","",G19-F19) -> 2 | I19: A. Reyes | J19: Direct | K19: Electrical | L19: Duplex Outlet 15A (10) | M19: EL-1510 | N19: 50 | O19: 13.4 | P19: =N19*O19 -> 670 | Q19: 0 | R19: =ROUND(P19*Q19,2) -> 0 | S19: =P19-R19 -> 670 | T19: =ROUND(S19*Assumptions!$B$2,2) -> 40.2 | U19: =S19+T19 -> 710.2 | V19: 14.1 | W19: =U19+V19 -> 724.3 | X19: Delivered | Y19: Reorder of prior PO
A20: Midwest | B20: Kentucky | C20: Lexington | D20: Oak Outfitters | E20: 41062 | F20: 46062 | G20: 46070 | H20: =IF(G20="","",G20-F20) -> 8 | I20: A. Reyes | J20: Online | K20: Hand Tools | L20: Framing Hammer 22 oz | M20: HT-2200 | N20: 25 | O20: 34.99 | P20: =N20*O20 -> 874.75 | Q20: 0.15 | R20: =ROUND(P20*Q20,2) -> 131.21 | S20: =P20-R20 -> 743.54 | T20: =ROUND(S20*Assumptions!$B$2,2) -> 44.61 | U20: =S20+T20 -> 788.15 | V20: 39.64 | W20: =U20+V20 -> 827.79 | X20: Shipped
A21: Midwest | B21: Kentucky | C21: Lexington | D21: Oak Outfitters | E21: 41063 | F21: 46189 | H21: =IF(G21="","",G21-F21) | I21: A. Reyes | J21: Direct | K21: Hand Tools | L21: Torpedo Level 9 in | M21: HT-0900 | N21: 6 | O21: 14.25 | P21: =N21*O21 -> 85.5 | Q21: 0.15 | R21: =ROUND(P21*Q21,2) -> 12.83 | S21: =P21-R21 -> 72.67 | T21: =ROUND(S21*Assumptions!$B$2,2) -> 4.36 | U21: =S21+T21 -> 77.03 | V21: 11.61 | W21: =U21+V21 -> 88.64 | X21: Backordered | Y21: New account
A22: Midwest | B22: Kentucky | C22: Lexington | D22: Oak Outfitters | E22: 41064 | F22: 46259 | G22: 46262 | H22: =IF(G22="","",G22-F22) -> 3 | I22: M. Okafor | J22: Direct | K22: Hand Tools | L22: Framing Hammer 22 oz | M22: HT-2200 | N22: 5 | O22: 34.99 | P22: =N22*O22 -> 174.95 | Q22: 0 | R22: =ROUND(P22*Q22,2) -> 0 | S22: =P22-R22 -> 174.95 | T22: =ROUND(S22*Assumptions!$B$2,2) -> 10.5 | U22: =S22+T22 -> 185.45 | V22: 15.99 | W22: =U22+V22 -> 201.44 | X22: Delivered | Y22: Partial shipment
A23: Midwest | B23: Kentucky | C23: Lexington | D23: Beacon Distributors | E23: 41069 | F23: 46230 | G23: 46233 | H23: =IF(G23="","",G23-F23) -> 3 | I23: M. Okafor | J23: Distributor | K23: Power Tools | L23: Cordless Drill 20V Kit | M23: PT-2001 | N23: 24 | O23: 129 | P23: =N23*O23 -> 3096 | Q23: 0.05 | R23: =ROUND(P23*Q23,2) -> 154.8 | S23: =P23-R23 -> 2941.2 | T23: =ROUND(S23*Assumptions!$B$2,2) -> 176.47 | U23: =S23+T23 -> 3117.67 | V23: 0.59 | W23: =U23+V23 -> 3118.26 | X23: Delivered
A24: Midwest | B24: Kentucky | C24: Lexington | D24: Beacon Distributors | E24: 41073 | F24: 46128 | G24: 46132 | H24: =IF(G24="","",G24-F24) -> 4 | I24: A. Reyes | J24: Direct | K24: Fasteners | L24: Hex Bolt 1/2 x 2, Zinc (100) | M24: FAS-1020 | N24: 15 | O24: 18.4 | P24: =N24*O24 -> 276 | Q24: 0.1 | R24: =ROUND(P24*Q24,2) -> 27.6 | S24: =P24-R24 -> 248.4 | T24: =ROUND(S24*Assumptions!$B$2,2) -> 14.9 | U24: =S24+T24 -> 263.3 | V24: 20.86 | W24: =U24+V24 -> 284.16 | X24: Shipped
A25: Midwest | B25: Kentucky | C25: Lexington | D25: Beacon Distributors | E25: 41078 | F25: 46160 | H25: =IF(G25="","",G25-F25) | I25: A. Reyes | J25: Distributor | K25: Hand Tools | L25: Torpedo Level 9 in | M25: HT-0900 | N25: 15 | O25: 14.25 | P25: =N25*O25 -> 213.75 | Q25: 0 | R25: =ROUND(P25*Q25,2) -> 0 | S25: =P25-R25 -> 213.75 | T25: =ROUND(S25*Assumptions!$B$2,2) -> 12.83 | U25: =S25+T25 -> 226.58 | V25: 19.31 | W25: =U25+V25 -> 245.89 | X25: Backordered | Y25: Partial shipment
A26: Midwest | B26: Ohio | C26: Cincinnati | D26: Ridge Fabrication | E26: 41085 | F26: 46220 | H26: =IF(G26="","",G26-F26) | I26: A. Reyes | J26: Online | K26: Electrical | L26: LED Shop Light 4 ft | M26: EL-0400 | N26: 20 | O26: 42 | P26: =N26*O26 -> 840 | Q26: 0.15 | R26: =ROUND(P26*Q26,2) -> 126 | S26: =P26-R26 -> 714 | T26: =ROUND(S26*Assumptions!$B$2,2) -> 42.84 | U26: =S26+T26 -> 756.84 | V26: 0 | W26: =U26+V26 -> 756.84 | X26: Open
A27: Midwest | B27: Ohio | C27: Cincinnati | D27: Ridge Fabrication | E27: 41088 | F27: 46099 | H27: =IF(G27="","",G27-F27) | I27: A. Reyes | J27: Direct | K27: Power Tools | L27: Circular Saw 7-1/4 in | M27: PT-7250 | N27: 50 | O27: 99 | P27: =N27*O27 -> 4950 | Q27: 0 | R27: =ROUND(P27*Q27,2) -> 0 | S27: =P27-R27 -> 4950 | T27: =ROUND(S27*Assumptions!$B$2,2) -> 297 | U27: =S27+T27 -> 5247 | V27: 0 | W27: =U27+V27 -> 5247 | X27: Open
A28: Midwest | B28: Ohio | C28: Cincinnati | D28: Ridge Fabrication | E28: 41093 | F28: 46100 | H28: =IF(G28="","",G28-F28) | I28: A. Reyes | J28: Online | K28: Hand Tools | L28: Adjustable Wrench 10 in | M28: HT-1000 | N28: 50 | O28: 19.5 | P28: =N28*O28 -> 975 | Q28: 0 | R28: =ROUND(P28*Q28,2) -> 0 | S28: =P28-R28 -> 975 | T28: =ROUND(S28*Assumptions!$B$2,2) -> 58.5 | U28: =S28+T28 -> 1033.5 | V28: 0 | W28: =U28+V28 -> 1033.5 | X28: Open | Y28: Customer pickup
A29: Midwest | B29: Ohio | C29: Cincinnati | D29: Ridge Fabrication | E29: 41098 | F29: 46032 | G29: 46036 | H29: =IF(G29="","",G29-F29) -> 4 | I29: M. Okafor | J29: Online | K29: Hand Tools | L29: Adjustable Wrench 10 in | M29: HT-1000 | N29: 8 | O29: 19.5 | P29: =N29*O29 -> 156 | Q29: 0.05 | R29: =ROUND(P29*Q29,2) -> 7.8 | S29: =P29-R29 -> 148.2 | T29: =ROUND(S29*Assumptions!$B$2,2) -> 8.89 | U29: =S29+T29 -> 157.09 | V29: 43.29 | W29: =U29+V29 -> 200.38 | X29: Delivered | Y29: Net 30 terms
A30: Midwest | B30: Ohio | C30: Cincinnati | D30: Riverside Distributors | E30: 41099 | F30: 46162 | G30: 46170 | H30: =IF(G30="","",G30-F30) -> 8 | I30: M. Okafor | J30: Online | K30: Power Tools | L30: Angle Grinder 4-1/2 in | M30: PT-4500 | N30: 3 | O30: 64.5 | P30: =N30*O30 -> 193.5 | Q30: 0.15 | R30: =ROUND(P30*Q30,2) -> 29.03 | S30: =P30-R30 -> 164.47 | T30: =ROUND(S30*Assumptions!$B$2,2) -> 9.87 | U30: =S30+T30 -> 174.34 | V30: 25.53 | W30: =U30+V30 -> 199.87 | X30: Shipped | Y30: Reorder of prior PO
A31: Midwest | B31: Ohio | C31: Cincinnati | D31: Riverside Distributors | E31: 41101 | F31: 46129 | G31: 46131 | H31: =IF(G31="","",G31-F31) -> 2 | I31: A. Reyes | J31: Online | K31: Fasteners | L31: Lag Screw 3/8 x 4 (50) | M31: FAS-3804 | N31: 12 | O31: 22.75 | P31: =N31*O31 -> 273 | Q31: 0 | R31: =ROUND(P31*Q31,2) -> 0 | S31: =P31-R31 -> 273 | T31: =ROUND(S31*Assumptions!$B$2,2) -> 16.38 | U31: =S31+T31 -> 289.38 | V31: 15.95 | W31: =U31+V31 -> 305.33 | X31: Delivered
A32: Midwest | B32: Ohio | C32: Cincinnati | D32: Riverside Distributors | E32: 41105 | F32: 46208 | G32: 46215 | H32: =IF(G32="","",G32-F32) -> 7 | I32: A. Reyes | J32: Online | K32: Electrical | L32: LED Shop Light 4 ft | M32: EL-0400 | N32: 24 | O32: 42 | P32: =N32*O32 -> 1008 | Q32: 0 | R32: =ROUND(P32*Q32,2) -> 0 | S32: =P32-R32 -> 1008 | T32: =ROUND(S32*Assumptions!$B$2,2) -> 60.48 | U32: =S32+T32 -> 1068.48 | V32: 1.03 | W32: =U32+V32 -> 1069.51 | X32: Delivered | Y32: New account
A33: Midwest | B33: Ohio | C33: Cincinnati | D33: Riverside Distributors | E33: 41112 | F33: 46210 | H33: =IF(G33="","",G33-F33) | I33: A. Reyes | J33: Direct | K33: Power Tools | L33: Angle Grinder 4-1/2 in | M33: PT-4500 | N33: 12 | O33: 64.5 | P33: =N33*O33 -> 774 | Q33: 0.05 | R33: =ROUND(P33*Q33,2) -> 38.7 | S33: =P33-R33 -> 735.3 | T33: =ROUND(S33*Assumptions!$B$2,2) -> 44.12 | U33: =S33+T33 -> 779.42 | V33: 40.94 | W33: =U33+V33 -> 820.36 | X33: Backordered
A34: Midwest | B34: Ohio | C34: Cincinnati | D34: Riverside Distributors | E34: 41115 | F34: 46261 | G34: 46263 | H34: =IF(G34="","",G34-F34) -> 2 | I34: M. Okafor | J34: Direct | K34: Fasteners | L34: Lag Screw 3/8 x 4 (50) | M34: FAS-3804 | N34: 24 | O34: 22.75 | P34: =N34*O34 -> 546 | Q34: 0 | R34: =ROUND(P34*Q34,2) -> 0 | S34: =P34-R34 -> 546 | T34: =ROUND(S34*Assumptions!$B$2,2) -> 32.76 | U34: =S34+T34 -> 578.76 | V34: 42.07 | W34: =U34+V34 -> 620.83 | X34: Delivered | Y34: Net 30 terms
A35: Midwest | B35: Ohio | C35: Cincinnati | D35: Riverside Distributors | E35: 41122 | F35: 46118 | G35: 46120 | H35: =IF(G35="","",G35-F35) -> 2 | I35: M. Okafor | J35: Online | K35: Safety | L35: Hard Hat, Type I | M35: SF-0001 | N35: 12 | O35: 21.95 | P35: =N35*O35 -> 263.4 | Q35: 0.05 | R35: =ROUND(P35*Q35,2) -> 13.17 | S35: =P35-R35 -> 250.23 | T35: =ROUND(S35*Assumptions!$B$2,2) -> 15.01 | U35: =S35+T35 -> 265.24 | V35: 34.42 | W35: =U35+V35 -> 299.66 | X35: Delivered | Y35: Partial shipment
A36: Midwest | B36: Ohio | C36: Cincinnati | D36: Cedar Farm & Feed | E36: 41123 | F36: 46037 | G36: 46041 | H36: =IF(G36="","",G36-F36) -> 4 | I36: M. Okafor | J36: Online | K36: Fasteners | L36: Deck Screw #10 x 3 (5 lb) | M36: FAS-1003 | N36: 25 | O36: 31.9 | P36: =N36*O36 -> 797.5 | Q36: 0 | R36: =ROUND(P36*Q36,2) -> 0 | S36: =P36-R36 -> 797.5 | T36: =ROUND(S36*Assumptions!$B$2,2) -> 47.85 | U36: =S36+T36 -> 845.35 | V36: 9.93 | W36: =U36+V36 -> 855.28 | X36: Delivered
A37: Midwest | B37: Ohio | C37: Cincinnati | D37: Cedar Farm & Feed | E37: 41128 | F37: 46211 | G37: 46213 | H37: =IF(G37="","",G37-F37) -> 2 | I37: A. Reyes | J37: Online | K37: Fasteners | L37: Deck Screw #10 x 3 (5 lb) | M37: FAS-1003 | N37: 6 | O37: 31.9 | P37: =N37*O37 -> 191.4 | Q37: 0.15 | R37: =ROUND(P37*Q37,2) -> 28.71 | S37: =P37-R37 -> 162.69 | T37: =ROUND(S37*Assumptions!$B$2,2) -> 9.76 | U37: =S37+T37 -> 172.45 | V37: 12.68 | W37: =U37+V37 -> 185.13 | X37: Delivered | Y37: New account
A38: Midwest | B38: Ohio | C38: Cincinnati | D38: Cedar Farm & Feed | E38: 41130 | F38: 46056 | G38: 46061 | H38: =IF(G38="","",G38-F38) -> 5 | I38: M. Okafor | J38: Distributor | K38: Electrical | L38: LED Shop Light 4 ft | M38: EL-0400 | N38: 30 | O38: 42 | P38: =N38*O38 -> 1260 | Q38: 0 | R38: =ROUND(P38*Q38,2) -> 0 | S38: =P38-R38 -> 1260 | T38: =ROUND(S38*Assumptions!$B$2,2) -> 75.6 | U38: =S38+T38 -> 1335.6 | V38: 17.68 | W38: =U38+V38 -> 1353.28 | X38: Shipped | Y38: Net 30 terms
A39: Midwest | B39: Ohio | C39: Columbus | D39: Maple Farm & Feed | E39: 41137 | F39: 46253 | H39: =IF(G39="","",G39-F39) | I39: M. Okafor | J39: Direct | K39: Electrical | L39: Duplex Outlet 15A (10) | M39: EL-1510 | N39: 3 | O39: 13.4 | P39: =N39*O39 -> 40.2 | Q39: 0.15 | R39: =ROUND(P39*Q39,2) -> 6.03 | S39: =P39-R39 -> 34.17 | T39: =ROUND(S39*Assumptions!$B$2,2) -> 2.05 | U39: =S39+T39 -> 36.22 | V39: 0 | W39: =U39+V39 -> 36.22 | X39: Open | Y39: Net 30 terms
A40: Midwest | B40: Ohio | C40: Columbus | D40: Maple Farm & Feed | E40: 41138 | F40: 46063 | G40: 46070 | H40: =IF(G40="","",G40-F40) -> 7 | I40: M. Okafor | J40: Direct | K40: Fasteners | L40: Deck Screw #10 x 3 (5 lb) | M40: FAS-1003 | N40: 30 | O40: 31.9 | P40: =N40*O40 -> 957 | Q40: 0 | R40: =ROUND(P40*Q40,2) -> 0 | S40: =P40-R40 -> 957 | T40: =ROUND(S40*Assumptions!$B$2,2) -> 57.42 | U40: =S40+T40 -> 1014.42 | V40: 15.02 | W40: =U40+V40 -> 1029.44 | X40: Delivered | Y40: Customer pickup
A41: Midwest | B41: Ohio | C41: Columbus | D41: Maple Farm & Feed | E41: 41140 | F41: 46054 | H41: =IF(G41="","",G41-F41) | I41: M. Okafor | J41: Online | K41: Fasteners | L41: Deck Screw #10 x 3 (5 lb) | M41: FAS-1003 | N41: 3 | O41: 31.9 | P41: =N41*O41 -> 95.7 | Q41: 0 | R41: =ROUND(P41*Q41,2) -> 0 | S41: =P41-R41 -> 95.7 | T41: =ROUND(S41*Assumptions!$B$2,2) -> 5.74 | U41: =S41+T41 -> 101.44 | V41: 28.22 | W41: =U41+V41 -> 129.66 | X41: Backordered | Y41: Net 30 terms
A42: Midwest | B42: Ohio | C42: Columbus | D42: Willow Distributors | E42: 41146 | F42: 46076 | G42: 46081 | H42: =IF(G42="","",G42-F42) -> 5 | I42: M. Okafor | J42: Online | K42: Power Tools | L42: Cordless Drill 20V Kit | M42: PT-2001 | N42: 8 | O42: 129 | P42: =N42*O42 -> 1032 | Q42: 0.15 | R42: =ROUND(P42*Q42,2) -> 154.8 | S42: =P42-R42 -> 877.2 | T42: =ROUND(S42*Assumptions!$B$2,2) -> 52.63 | U42: =S42+T42 -> 929.83 | V42: 1.13 | W42: =U42+V42 -> 930.96 | X42: Delivered | Y42: Damaged in transit; replaced
A43: Midwest | B43: Ohio | C43: Columbus | D43: Willow Distributors | E43: 41148 | F43: 46167 | G43: 46171 | H43: =IF(G43="","",G43-F43) -> 4 | I43: M. Okafor | J43: Direct | K43: Power Tools | L43: Circular Saw 7-1/4 in | M43: PT-7250 | N43: 50 | O43: 99 | P43: =N43*O43 -> 4950 | Q43: 0.15 | R43: =ROUND(P43*Q43,2) -> 742.5 | S43: =P43-R43 -> 4207.5 | T43: =ROUND(S43*Assumptions!$B$2,2) -> 252.45 | U43: =S43+T43 -> 4459.95 | V43: 21.4 | W43: =U43+V43 -> 4481.35 | X43: Delivered
A44: Midwest | B44: Ohio | C44: Columbus | D44: Willow Distributors | E44: 41150 | F44: 46084 | G44: 46090 | H44: =IF(G44="","",G44-F44) -> 6 | I44: M. Okafor | J44: Online | K44: Safety | L44: Hard Hat, Type I | M44: SF-0001 | N44: 24 | O44: 21.95 | P44: =N44*O44 -> 526.8 | Q44: 0.1 | R44: =ROUND(P44*Q44,2) -> 52.68 | S44: =P44-R44 -> 474.12 | T44: =ROUND(S44*Assumptions!$B$2,2) -> 28.45 | U44: =S44+T44 -> 502.57 | V44: 44.54 | W44: =U44+V44 -> 547.11 | X44: Delivered
A45: Midwest | B45: Ohio | C45: Columbus | D45: Willow Distributors | E45: 41151 | F45: 46133 | G45: 46137 | H45: =IF(G45="","",G45-F45) -> 4 | I45: M. Okafor | J45: Direct | K45: Electrical | L45: LED Shop Light 4 ft | M45: EL-0400 | N45: 50 | O45: 42 | P45: =N45*O45 -> 2100 | Q45: 0 | R45: =ROUND(P45*Q45,2) -> 0 | S45: =P45-R45 -> 2100 | T45: =ROUND(S45*Assumptions!$B$2,2) -> 126 | U45: =S45+T45 -> 2226 | V45: 12.42 | W45: =U45+V45 -> 2238.42 | X45: Shipped
A46: Midwest | B46: Ohio | C46: Columbus | D46: Pioneer Building Products | E46: 41152 | F46: 46188 | G46: 46190 | H46: =IF(G46="","",G46-F46) -> 2 | I46: A. Reyes | J46: Direct | K46: Safety | L46: Nitrile Gloves, L (100) | M46: SF-0100 | N46: 15 | O46: 16.8 | P46: =N46*O46 -> 252 | Q46: 0.05 | R46: =ROUND(P46*Q46,2) -> 12.6 | S46: =P46-R46 -> 239.4 | T46: =ROUND(S46*Assumptions!$B$2,2) -> 14.36 | U46: =S46+T46 -> 253.76 | V46: 31.2 | W46: =U46+V46 -> 284.96 | X46: Delivered
A47: Midwest | B47: Ohio | C47: Columbus | D47: Pioneer Building Products | E47: 41155 | F47: 46029 | G47: 46034 | H47: =IF(G47="","",G47-F47) -> 5 | I47: M. Okafor | J47: Direct | K47: Electrical | L47: Romex 12/2 NM-B 250 ft | M47: EL-1225 | N47: 1 | O47: 118 | P47: =N47*O47 -> 118 | Q47: 0 | R47: =ROUND(P47*Q47,2) -> 0 | S47: =P47-R47 -> 118 | T47: =ROUND(S47*Assumptions!$B$2,2) -> 7.08 | U47: =S47+T47 -> 125.08 | V47: 15.43 | W47: =U47+V47 -> 140.51 | X47: Delivered
A48: Midwest | B48: Ohio | C48: Columbus | D48: Pioneer Building Products | E48: 41156 | F48: 46208 | H48: =IF(G48="","",G48-F48) | I48: M. Okafor | J48: Online | K48: Safety | L48: Hard Hat, Type I | M48: SF-0001 | N48: 8 | O48: 21.95 | P48: =N48*O48 -> 175.6 | Q48: 0.05 | R48: =ROUND(P48*Q48,2) -> 8.78 | S48: =P48-R48 -> 166.82 | T48: =ROUND(S48*Assumptions!$B$2,2) -> 10.01 | U48: =S48+T48 -> 176.83 | V48: 0 | W48: =U48+V48 -> 176.83 | X48: Open
A49: Midwest | B49: Indiana | C49: Indianapolis | D49: Prairie Outfitters | E49: 41163 | F49: 46230 | H49: =IF(G49="","",G49-F49) | I49: A. Reyes | J49: Direct | K49: Safety | L49: Nitrile Gloves, L (100) | M49: SF-0100 | N49: 5 | O49: 16.8 | P49: =N49*O49 -> 84 | Q49: 0.1 | R49: =ROUND(P49*Q49,2) -> 8.4 | S49: =P49-R49 -> 75.6 | T49: =ROUND(S49*Assumptions!$B$2,2) -> 4.54 | U49: =S49+T49 -> 80.14 | V49: 0 | W49: =U49+V49 -> 80.14 | X49: Open | Y49: Rush order
A50: Midwest | B50: Indiana | C50: Indianapolis | D50: Prairie Outfitters | E50: 41164 | F50: 46127 | G50: 46136 | H50: =IF(G50="","",G50-F50) -> 9 | I50: A. Reyes | J50: Distributor | K50: Electrical | L50: Duplex Outlet 15A (10) | M50: EL-1510 | N50: 15 | O50: 13.4 | P50: =N50*O50 -> 201 | Q50: 0 | R50: =ROUND(P50*Q50,2) -> 0 | S50: =P50-R50 -> 201 | T50: =ROUND(S50*Assumptions!$B$2,2) -> 12.06 | U50: =S50+T50 -> 213.06 | V50: 17.4 | W50: =U50+V50 -> 230.46 | X50: Delivered | Y50: Rush order
A51: Midwest | B51: Indiana | C51: Indianapolis | D51: Falcon Distributors | E51: 41171 | F51: 46049 | G51: 46056 | H51: =IF(G51="","",G51-F51) -> 7 | I51: M. Okafor | J51: Online | K51: Safety | L51: Hard Hat, Type I | M51: SF-0001 | N51: 15 | O51: 21.95 | P51: =N51*O51 -> 329.25 | Q51: 0.1 | R51: =ROUND(P51*Q51,2) -> 32.93 | S51: =P51-R51 -> 296.32 | T51: =ROUND(S51*Assumptions!$B$2,2) -> 17.78 | U51: =S51+T51 -> 314.1 | V51: 12.96 | W51: =U51+V51 -> 327.06 | X51: Shipped | Y51: Reorder of prior PO
A52: Midwest | B52: Indiana | C52: Indianapolis | D52: Falcon Distributors | E52: 41173 | F52: 46126 | G52: 46132 | H52: =IF(G52="","",G52-F52) -> 6 | I52: M. Okafor | J52: Online | K52: Electrical | L52: Duplex Outlet 15A (10) | M52: EL-1510 | N52: 40 | O52: 13.4 | P52: =N52*O52 -> 536 | Q52: 0.05 | R52: =ROUND(P52*Q52,2) -> 26.8 | S52: =P52-R52 -> 509.2 | T52: =ROUND(S52*Assumptions!$B$2,2) -> 30.55 | U52: =S52+T52 -> 539.75 | V52: 36.48 | W52: =U52+V52 -> 576.23 | X52: Delivered | Y52: Damaged in transit; replaced
A53: Midwest | B53: Indiana | C53: Indianapolis | D53: Falcon Distributors | E53: 41179 | F53: 46179 | G53: 46183 | H53: =IF(G53="","",G53-F53) -> 4 | I53: A. Reyes | J53: Online | K53: Electrical | L53: LED Shop Light 4 ft | M53: EL-0400 | N53: 6 | O53: 42 | P53: =N53*O53 -> 252 | Q53: 0.05 | R53: =ROUND(P53*Q53,2) -> 12.6 | S53: =P53-R53 -> 239.4 | T53: =ROUND(S53*Assumptions!$B$2,2) -> 14.36 | U53: =S53+T53 -> 253.76 | V53: 31.85 | W53: =U53+V53 -> 285.61 | X53: Delivered
A54: Midwest | B54: Indiana | C54: Indianapolis | D54: Falcon Distributors | E54: 41184 | F54: 46225 | G54: 46229 | H54: =IF(G54="","",G54-F54) -> 4 | I54: M. Okafor | J54: Distributor | K54: Hand Tools | L54: Framing Hammer 22 oz | M54: HT-2200 | N54: 4 | O54: 34.99 | P54: =N54*O54 -> 139.96 | Q54: 0.05 | R54: =ROUND(P54*Q54,2) -> 7 | S54: =P54-R54 -> 132.96 | T54: =ROUND(S54*Assumptions!$B$2,2) -> 7.98 | U54: =S54+T54 -> 140.94 | V54: 32.83 | W54: =U54+V54 -> 173.77 | X54: Delivered | Y54: Customer pickup
A55: Midwest | B55: Indiana | C55: Indianapolis | D55: Falcon Distributors | E55: 41185 | F55: 46104 | G55: 46106 | H55: =IF(G55="","",G55-F55) -> 2 | I55: A. Reyes | J55: Direct | K55: Safety | L55: Nitrile Gloves, L (100) | M55: SF-0100 | N55: 15 | O55: 16.8 | P55: =N55*O55 -> 252 | Q55: 0 | R55: =ROUND(P55*Q55,2) -> 0 | S55: =P55-R55 -> 252 | T55: =ROUND(S55*Assumptions!$B$2,2) -> 15.12 | U55: =S55+T55 -> 267.12 | V55: 14.1 | W55: =U55+V55 -> 281.22 | X55: Shipped | Y55: New account
A56: Midwest | B56: Indiana | C56: Indianapolis | D56: Falcon Distributors | E56: 41191 | F56: 46262 | G56: 46269 | H56: =IF(G56="","",G56-F56) -> 7 | I56: M. Okafor | J56: Distributor | K56: Hand Tools | L56: Adjustable Wrench 10 in | M56: HT-1000 | N56: 10 | O56: 19.5 | P56: =N56*O56 -> 195 | Q56: 0 | R56: =ROUND(P56*Q56,2) -> 0 | S56: =P56-R56 -> 195 | T56: =ROUND(S56*Assumptions!$B$2,2) -> 11.7 | U56: =S56+T56 -> 206.7 | V56: 29.79 | W56: =U56+V56 -> 236.49 | X56: Shipped | Y56: Damaged in transit; replaced
A57: South | B57: Tennessee | C57: Nashville | D57: Falcon Supply Co | E57: 41195 | F57: 46055 | H57: =IF(G57="","",G57-F57) | I57: J. Whitfield | J57: Online | K57: Power Tools | L57: Angle Grinder 4-1/2 in | M57: PT-4500 | N57: 12 | O57: 64.5 | P57: =N57*O57 -> 774 | Q57: 0.1 | R57: =ROUND(P57*Q57,2) -> 77.4 | S57: =P57-R57 -> 696.6 | T57: =ROUND(S57*Assumptions!$B$2,2) -> 41.8 | U57: =S57+T57 -> 738.4 | V57: 39.51 | W57: =U57+V57 -> 777.91 | X57: Backordered
A58: South | B58: Tennessee | C58: Nashville | D58: Falcon Supply Co | E58: 41198 | F58: 46073 | H58: =IF(G58="","",G58-F58) | I58: J. Whitfield | J58: Distributor | K58: Safety | L58: Safety Glasses, Clear (12) | M58: SF-0012 | N58: 40 | O58: 27.6 | P58: =N58*O58 -> 1104 | Q58: 0.1 | R58: =ROUND(P58*Q58,2) -> 110.4 | S58: =P58-R58 -> 993.6 | T58: =ROUND(S58*Assumptions!$B$2,2) -> 59.62 | U58: =S58+T58 -> 1053.22 | V58: 0 | W58: =U58+V58 -> 1053.22 | X58: Open
A59: South | B59: Tennessee | C59: Nashville | D59: Falcon Supply Co | E59: 41202 | F59: 46099 | G59: 46106 | H59: =IF(G59="","",G59-F59) -> 7 | I59: S. Nakamura | J59: Direct | K59: Fasteners | L59: Lag Screw 3/8 x 4 (50) | M59: FAS-3804 | N59: 6 | O59: 22.75 | P59: =N59*O59 -> 136.5 | Q59: 0 | R59: =ROUND(P59*Q59,2) -> 0 | S59: =P59-R59 -> 136.5 | T59: =ROUND(S59*Assumptions!$B$2,2) -> 8.19 | U59: =S59+T59 -> 144.69 | V59: 27.32 | W59: =U59+V59 -> 172.01 | X59: Delivered | Y59: Partial shipment
A60: South | B60: Tennessee | C60: Nashville | D60: Falcon Supply Co | E60: 41207 | F60: 46242 | G60: 46250 | H60: =IF(G60="","",G60-F60) -> 8 | I60: J. Whitfield | J60: Direct | K60: Fasteners | L60: Deck Screw #10 x 3 (5 lb) | M60: FAS-1003 | N60: 6 | O60: 31.9 | P60: =N60*O60 -> 191.4 | Q60: 0.15 | R60: =ROUND(P60*Q60,2) -> 28.71 | S60: =P60-R60 -> 162.69 | T60: =ROUND(S60*Assumptions!$B$2,2) -> 9.76 | U60: =S60+T60 -> 172.45 | V60: 0.88 | W60: =U60+V60 -> 173.33 | X60: Delivered | Y60: Reorder of prior PO
A61: South | B61: Tennessee | C61: Nashville | D61: Falcon Supply Co | E61: 41209 | F61: 46119 | H61: =IF(G61="","",G61-F61) | I61: S. Nakamura | J61: Online | K61: Safety | L61: Safety Glasses, Clear (12) | M61: SF-0012 | N61: 50 | O61: 27.6 | P61: =N61*O61 -> 1380 | Q61: 0.05 | R61: =ROUND(P61*Q61,2) -> 69 | S61: =P61-R61 -> 1311 | T61: =ROUND(S61*Assumptions!$B$2,2) -> 78.66 | U61: =S61+T61 -> 1389.66 | V61: 0 | W61: =U61+V61 -> 1389.66 | X61: Open | Y61: Net 30 terms
A62: South | B62: Tennessee | C62: Nashville | D62: Granite Outfitters | E62: 41213 | F62: 46213 | H62: =IF(G62="","",G62-F62) | I62: J. Whitfield | J62: Online | K62: Electrical | L62: LED Shop Light 4 ft | M62: EL-0400 | N62: 3 | O62: 42 | P62: =N62*O62 -> 126 | Q62: 0.15 | R62: =ROUND(P62*Q62,2) -> 18.9 | S62: =P62-R62 -> 107.1 | T62: =ROUND(S62*Assumptions!$B$2,2) -> 6.43 | U62: =S62+T62 -> 113.53 | V62: 14.67 | W62: =U62+V62 -> 128.2 | X62: Backordered | Y62: Damaged in transit; replaced
A63: South | B63: Tennessee | C63: Nashville | D63: Granite Outfitters | E63: 41217 | F63: 46068 | H63: =IF(G63="","",G63-F63) | I63: J. Whitfield | J63: Online | K63: Hand Tools | L63: Adjustable Wrench 10 in | M63: HT-1000 | N63: 1 | O63: 19.5 | P63: =N63*O63 -> 19.5 | Q63: 0.1 | R63: =ROUND(P63*Q63,2) -> 1.95 | S63: =P63-R63 -> 17.55 | T63: =ROUND(S63*Assumptions!$B$2,2) -> 1.05 | U63: =S63+T63 -> 18.6 | V63: 0 | W63: =U63+V63 -> 18.6 | X63: Open | Y63: Rush order
A64: South | B64: Tennessee | C64: Nashville | D64: Granite Outfitters | E64: 41220 | F64: 46172 | G64: 46181 | H64: =IF(G64="","",G64-F64) -> 9 | I64: J. Whitfield | J64: Distributor | K64: Electrical | L64: Duplex Outlet 15A (10) | M64: EL-1510 | N64: 20 | O64: 13.4 | P64: =N64*O64 -> 268 | Q64: 0.1 | R64: =ROUND(P64*Q64,2) -> 26.8 | S64: =P64-R64 -> 241.2 | T64: =ROUND(S64*Assumptions!$B$2,2) -> 14.47 | U64: =S64+T64 -> 255.67 | V64: 41.5 | W64: =U64+V64 -> 297.17 | X64: Shipped
A65: South | B65: Tennessee | C65: Nashville | D65: Granite Outfitters | E65: 41227 | F65: 46112 | G65: 46116 | H65: =IF(G65="","",G65-F65) -> 4 | I65: J. Whitfield | J65: Online | K65: Fasteners | L65: Lag Screw 3/8 x 4 (50) | M65: FAS-3804 | N65: 2 | O65: 22.75 | P65: =N65*O65 -> 45.5 | Q65: 0.15 | R65: =ROUND(P65*Q65,2) -> 6.83 | S65: =P65-R65 -> 38.67 | T65: =ROUND(S65*Assumptions!$B$2,2) -> 2.32 | U65: =S65+T65 -> 40.99 | V65: 40.22 | W65: =U65+V65 -> 81.21 | X65: Delivered
A66: South | B66: Tennessee | C66: Nashville | D66: Granite Outfitters | E66: 41230 | F66: 46235 | G66: 46238 | H66: =IF(G66="","",G66-F66) -> 3 | I66: S. Nakamura | J66: Direct | K66: Safety | L66: Nitrile Gloves, L (100) | M66: SF-0100 | N66: 25 | O66: 16.8 | P66: =N66*O66 -> 420 | Q66: 0.05 | R66: =ROUND(P66*Q66,2) -> 21 | S66: =P66-R66 -> 399 | T66: =ROUND(S66*Assumptions!$B$2,2) -> 23.94 | U66: =S66+T66 -> 422.94 | V66: 25.38 | W66: =U66+V66 -> 448.32 | X66: Shipped | Y66: Net 30 terms
A67: South | B67: Tennessee | C67: Memphis | D67: Prairie Distributors | E67: 41233 | F67: 46162 | G67: 46167 | H67: =IF(G67="","",G67-F67) -> 5 | I67: J. Whitfield | J67: Direct | K67: Safety | L67: Nitrile Gloves, L (100) | M67: SF-0100 | N67: 4 | O67: 16.8 | P67: =N67*O67 -> 67.2 | Q67: 0 | R67: =ROUND(P67*Q67,2) -> 0 | S67: =P67-R67 -> 67.2 | T67: =ROUND(S67*Assumptions!$B$2,2) -> 4.03 | U67: =S67+T67 -> 71.23 | V67: 31.61 | W67: =U67+V67 -> 102.84 | X67: Delivered
A68: South | B68: Tennessee | C68: Memphis | D68: Prairie Distributors | E68: 41240 | F68: 46162 | H68: =IF(G68="","",G68-F68) | I68: S. Nakamura | J68: Direct | K68: Fasteners | L68: Lag Screw 3/8 x 4 (50) | M68: FAS-3804 | N68: 12 | O68: 22.75 | P68: =N68*O68 -> 273 | Q68: 0.1 | R68: =ROUND(P68*Q68,2) -> 27.3 | S68: =P68-R68 -> 245.7 | T68: =ROUND(S68*Assumptions!$B$2,2) -> 14.74 | U68: =S68+T68 -> 260.44 | V68: 4.92 | W68: =U68+V68 -> 265.36 | X68: Backordered | Y68: Damaged in transit; replaced
A69: South | B69: Tennessee | C69: Memphis | D69: Willow Hardware | E69: 41243 | F69: 46097 | G69: 46103 | H69: =IF(G69="","",G69-F69) -> 6 | I69: S. Nakamura | J69: Distributor | K69: Electrical | L69: Romex 12/2 NM-B 250 ft | M69: EL-1225 | N69: 6 | O69: 118 | P69: =N69*O69 -> 708 | Q69: 0.05 | R69: =ROUND(P69*Q69,2) -> 35.4 | S69: =P69-R69 -> 672.6 | T69: =ROUND(S69*Assumptions!$B$2,2) -> 40.36 | U69: =S69+T69 -> 712.96 | V69: 27.9 | W69: =U69+V69 -> 740.86 | X69: Delivered | Y69: Rush order
A70: South | B70: Tennessee | C70: Memphis | D70: Willow Hardware | E70: 41245 | F70: 46176 | G70: 46181 | H70: =IF(G70="","",G70-F70) -> 5 | I70: S. Nakamura | J70: Direct | K70: Fasteners | L70: Hex Bolt 1/2 x 2, Zinc (100) | M70: FAS-1020 | N70: 12 | O70: 18.4 | P70: =N70*O70 -> 220.8 | Q70: 0 | R70: =ROUND(P70*Q70,2) -> 0 | S70: =P70-R70 -> 220.8 | T70: =ROUND(S70*Assumptions!$B$2,2) -> 13.25 | U70: =S70+T70 -> 234.05 | V70: 27.93 | W70: =U70+V70 -> 261.98 | X70: Delivered | Y70: Damaged in transit; replaced
A71: South | B71: Tennessee | C71: Memphis | D71: Willow Hardware | E71: 41247 | F71: 46126 | H71: =IF(G71="","",G71-F71) | I71: S. Nakamura | J71: Direct | K71: Electrical | L71: Duplex Outlet 15A (10) | M71: EL-1510 | N71: 5 | O71: 13.4 | P71: =N71*O71 -> 67 | Q71: 0.1 | R71: =ROUND(P71*Q71,2) -> 6.7 | S71: =P71-R71 -> 60.3 | T71: =ROUND(S71*Assumptions!$B$2,2) -> 3.62 | U71: =S71+T71 -> 63.92 | V71: 0 | W71: =U71+V71 -> 63.92 | X71: Open
A72: South | B72: Tennessee | C72: Memphis | D72: Willow Hardware | E72: 41248 | F72: 46102 | G72: 46109 | H72: =IF(G72="","",G72-F72) -> 7 | I72: J. Whitfield | J72: Distributor | K72: Electrical | L72: Romex 12/2 NM-B 250 ft | M72: EL-1225 | N72: 3 | O72: 118 | P72: =N72*O72 -> 354 | Q72: 0 | R72: =ROUND(P72*Q72,2) -> 0 | S72: =P72-R72 -> 354 | T72: =ROUND(S72*Assumptions!$B$2,2) -> 21.24 | U72: =S72+T72 -> 375.24 | V72: 14.42 | W72: =U72+V72 -> 389.66 | X72: Delivered | Y72: Partial shipment
A73: South | B73: Tennessee | C73: Memphis | D73: Willow Hardware | E73: 41249 | F73: 46077 | G73: 46079 | H73: =IF(G73="","",G73-F73) -> 2 | I73: S. Nakamura | J73: Distributor | K73: Hand Tools | L73: Torpedo Level 9 in | M73: HT-0900 | N73: 10 | O73: 14.25 | P73: =N73*O73 -> 142.5 | Q73: 0 | R73: =ROUND(P73*Q73,2) -> 0 | S73: =P73-R73 -> 142.5 | T73: =ROUND(S73*Assumptions!$B$2,2) -> 8.55 | U73: =S73+T73 -> 151.05 | V73: 32.5 | W73: =U73+V73 -> 183.55 | X73: Delivered | Y73: Reorder of prior PO
A74: South | B74: Tennessee | C74: Memphis | D74: Willow Hardware | E74: 41250 | F74: 46078 | G74: 46082 | H74: =IF(G74="","",G74-F74) -> 4 | I74: S. Nakamura | J74: Direct | K74: Safety | L74: Nitrile Gloves, L (100) | M74: SF-0100 | N74: 1 | O74: 16.8 | P74: =N74*O74 -> 16.8 | Q74: 0 | R74: =ROUND(P74*Q74,2) -> 0 | S74: =P74-R74 -> 16.8 | T74: =ROUND(S74*Assumptions!$B$2,2) -> 1.01 | U74: =S74+T74 -> 17.81 | V74: 12.16 | W74: =U74+V74 -> 29.97 | X74: Delivered
A75: South | B75: Georgia | C75: Atlanta | D75: Summit Fabrication | E75: 41256 | F75: 46192 | H75: =IF(G75="","",G75-F75) | I75: J. Whitfield | J75: Online | K75: Electrical | L75: Duplex Outlet 15A (10) | M75: EL-1510 | N75: 15 | O75: 13.4 | P75: =N75*O75 -> 201 | Q75: 0.1 | R75: =ROUND(P75*Q75,2) -> 20.1 | S75: =P75-R75 -> 180.9 | T75: =ROUND(S75*Assumptions!$B$2,2) -> 10.85 | U75: =S75+T75 -> 191.75 | V75: 0 | W75: =U75+V75 -> 191.75 | X75: Open
A76: South | B76: Georgia | C76: Atlanta | D76: Summit Fabrication | E76: 41259 | F76: 46206 | G76: 46213 | H76: =IF(G76="","",G76-F76) -> 7 | I76: J. Whitfield | J76: Direct | K76: Hand Tools | L76: Torpedo Level 9 in | M76: HT-0900 | N76: 12 | O76: 14.25 | P76: =N76*O76 -> 171 | Q76: 0 | R76: =ROUND(P76*Q76,2) -> 0 | S76: =P76-R76 -> 171 | T76: =ROUND(S76*Assumptions!$B$2,2) -> 10.26 | U76: =S76+T76 -> 181.26 | V76: 17.37 | W76: =U76+V76 -> 198.63 | X76: Shipped
A77: South | B77: Georgia | C77: Atlanta | D77: Summit Fabrication | E77: 41260 | F77: 46130 | G77: 46133 | H77: =IF(G77="","",G77-F77) -> 3 | I77: S. Nakamura | J77: Distributor | K77: Fasteners | L77: Lag Screw 3/8 x 4 (50) | M77: FAS-3804 | N77: 12 | O77: 22.75 | P77: =N77*O77 -> 273 | Q77: 0.15 | R77: =ROUND(P77*Q77,2) -> 40.95 | S77: =P77-R77 -> 232.05 | T77: =ROUND(S77*Assumptions!$B$2,2) -> 13.92 | U77: =S77+T77 -> 245.97 | V77: 10.8 | W77: =U77+V77 -> 256.77 | X77: Shipped | Y77: Rush order
A78: South | B78: Georgia | C78: Atlanta | D78: Summit Fabrication | E78: 41267 | F78: 46073 | G78: 46080 | H78: =IF(G78="","",G78-F78) -> 7 | I78: J. Whitfield | J78: Direct | K78: Safety | L78: Safety Glasses, Clear (12) | M78: SF-0012 | N78: 1 | O78: 27.6 | P78: =N78*O78 -> 27.6 | Q78: 0 | R78: =ROUND(P78*Q78,2) -> 0 | S78: =P78-R78 -> 27.6 | T78: =ROUND(S78*Assumptions!$B$2,2) -> 1.66 | U78: =S78+T78 -> 29.26 | V78: 5.98 | W78: =U78+V78 -> 35.24 | X78: Delivered | Y78: New account
A79: South | B79: Georgia | C79: Atlanta | D79: Summit Farm & Feed | E79: 41273 | F79: 46192 | H79: =IF(G79="","",G79-F79) | I79: J. Whitfield | J79: Online | K79: Safety | L79: Nitrile Gloves, L (100) | M79: SF-0100 | N79: 4 | O79: 16.8 | P79: =N79*O79 -> 67.2 | Q79: 0.1 | R79: =ROUND(P79*Q79,2) -> 6.72 | S79: =P79-R79 -> 60.48 | T79: =ROUND(S79*Assumptions!$B$2,2) -> 3.63 | U79: =S79+T79 -> 64.11 | V79: 0.65 | W79: =U79+V79 -> 64.76 | X79: Backordered | Y79: Damaged in transit; replaced
A80: South | B80: Georgia | C80: Atlanta | D80: Summit Farm & Feed | E80: 41276 | F80: 46100 | G80: 46106 | H80: =IF(G80="","",G80-F80) -> 6 | I80: S. Nakamura | J80: Online | K80: Electrical | L80: Duplex Outlet 15A (10) | M80: EL-1510 | N80: 40 | O80: 13.4 | P80: =N80*O80 -> 536 | Q80: 0.15 | R80: =ROUND(P80*Q80,2) -> 80.4 | S80: =P80-R80 -> 455.6 | T80: =ROUND(S80*Assumptions!$B$2,2) -> 27.34 | U80: =S80+T80 -> 482.94 | V80: 37.98 | W80: =U80+V80 -> 520.92 | X80: Shipped | Y80: Reorder of prior PO
A81: South | B81: Georgia | C81: Atlanta | D81: Summit Farm & Feed | E81: 41277 | F81: 46085 | G81: 46087 | H81: =IF(G81="","",G81-F81) -> 2 | I81: S. Nakamura | J81: Distributor | K81: Hand Tools | L81: Framing Hammer 22 oz | M81: HT-2200 | N81: 30 | O81: 34.99 | P81: =N81*O81 -> 1049.7 | Q81: 0.1 | R81: =ROUND(P81*Q81,2) -> 104.97 | S81: =P81-R81 -> 944.73 | T81: =ROUND(S81*Assumptions!$B$2,2) -> 56.68 | U81: =S81+T81 -> 1001.41 | V81: 4.37 | W81: =U81+V81 -> 1005.78 | X81: Delivered | Y81: New account
A82: South | B82: Georgia | C82: Atlanta | D82: Summit Farm & Feed | E82: 41279 | F82: 46144 | H82: =IF(G82="","",G82-F82) | I82: S. Nakamura | J82: Distributor | K82: Safety | L82: Nitrile Gloves, L (100) | M82: SF-0100 | N82: 6 | O82: 16.8 | P82: =N82*O82 -> 100.8 | Q82: 0.05 | R82: =ROUND(P82*Q82,2) -> 5.04 | S82: =P82-R82 -> 95.76 | T82: =ROUND(S82*Assumptions!$B$2,2) -> 5.75 | U82: =S82+T82 -> 101.51 | V82: 3.17 | W82: =U82+V82 -> 104.68 | X82: Backordered | Y82: Customer pickup
A83: South | B83: Georgia | C83: Atlanta | D83: Ironwood Fabrication | E83: 41283 | F83: 46261 | G83: 46263 | H83: =IF(G83="","",G83-F83) -> 2 | I83: J. Whitfield | J83: Online | K83: Fasteners | L83: Lag Screw 3/8 x 4 (50) | M83: FAS-3804 | N83: 24 | O83: 22.75 | P83: =N83*O83 -> 546 | Q83: 0 | R83: =ROUND(P83*Q83,2) -> 0 | S83: =P83-R83 -> 546 | T83: =ROUND(S83*Assumptions!$B$2,2) -> 32.76 | U83: =S83+T83 -> 578.76 | V83: 17.99 | W83: =U83+V83 -> 596.75 | X83: Shipped | Y83: Customer pickup
A84: South | B84: Georgia | C84: Atlanta | D84: Ironwood Fabrication | E84: 41285 | F84: 46033 | G84: 46039 | H84: =IF(G84="","",G84-F84) -> 6 | I84: J. Whitfield | J84: Online | K84: Power Tools | L84: Circular Saw 7-1/4 in | M84: PT-7250 | N84: 4 | O84: 99 | P84: =N84*O84 -> 396 | Q84: 0.05 | R84: =ROUND(P84*Q84,2) -> 19.8 | S84: =P84-R84 -> 376.2 | T84: =ROUND(S84*Assumptions!$B$2,2) -> 22.57 | U84: =S84+T84 -> 398.77 | V84: 4.5 | W84: =U84+V84 -> 403.27 | X84: Shipped
A85: South | B85: Georgia | C85: Atlanta | D85: Ironwood Fabrication | E85: 41289 | F85: 46185 | H85: =IF(G85="","",G85-F85) | I85: S. Nakamura | J85: Distributor | K85: Safety | L85: Hard Hat, Type I | M85: SF-0001 | N85: 1 | O85: 21.95 | P85: =N85*O85 -> 21.95 | Q85: 0.15 | R85: =ROUND(P85*Q85,2) -> 3.29 | S85: =P85-R85 -> 18.66 | T85: =ROUND(S85*Assumptions!$B$2,2) -> 1.12 | U85: =S85+T85 -> 19.78 | V85: 38.51 | W85: =U85+V85 -> 58.29 | X85: Backordered
A86: South | B86: Georgia | C86: Atlanta | D86: Ironwood Fabrication | E86: 41292 | F86: 46095 | G86: 46096 | H86: =IF(G86="","",G86-F86) -> 1 | I86: J. Whitfield | J86: Distributor | K86: Electrical | L86: Romex 12/2 NM-B 250 ft | M86: EL-1225 | N86: 5 | O86: 118 | P86: =N86*O86 -> 590 | Q86: 0 | R86: =ROUND(P86*Q86,2) -> 0 | S86: =P86-R86 -> 590 | T86: =ROUND(S86*Assumptions!$B$2,2) -> 35.4 | U86: =S86+T86 -> 625.4 | V86: 29.39 | W86: =U86+V86 -> 654.79 | X86: Delivered | Y86: Partial shipment
A87: South | B87: Georgia | C87: Atlanta | D87: Ironwood Fabrication | E87: 41296 | F87: 46229 | H87: =IF(G87="","",G87-F87) | I87: S. Nakamura | J87: Distributor | K87: Fasteners | L87: Deck Screw #10 x 3 (5 lb) | M87: FAS-1003 | N87: 50 | O87: 31.9 | P87: =N87*O87 -> 1595 | Q87: 0 | R87: =ROUND(P87*Q87,2) -> 0 | S87: =P87-R87 -> 1595 | T87: =ROUND(S87*Assumptions!$B$2,2) -> 95.7 | U87: =S87+T87 -> 1690.7 | V87: 0 | W87: =U87+V87 -> 1690.7 | X87: Open
A88: South | B88: Texas | C88: Dallas | D88: Falcon Building Products | E88: 41302 | F88: 46031 | H88: =IF(G88="","",G88-F88) | I88: S. Nakamura | J88: Direct | K88: Safety | L88: Safety Glasses, Clear (12) | M88: SF-0012 | N88: 25 | O88: 27.6 | P88: =N88*O88 -> 690 | Q88: 0.15 | R88: =ROUND(P88*Q88,2) -> 103.5 | S88: =P88-R88 -> 586.5 | T88: =ROUND(S88*Assumptions!$B$2,2) -> 35.19 | U88: =S88+T88 -> 621.69 | V88: 2.6 | W88: =U88+V88 -> 624.29 | X88: Backordered | Y88: Partial shipment
A89: South | B89: Texas | C89: Dallas | D89: Falcon Building Products | E89: 41304 | F89: 46030 | H89: =IF(G89="","",G89-F89) | I89: S. Nakamura | J89: Online | K89: Hand Tools | L89: Framing Hammer 22 oz | M89: HT-2200 | N89: 50 | O89: 34.99 | P89: =N89*O89 -> 1749.5 | Q89: 0 | R89: =ROUND(P89*Q89,2) -> 0 | S89: =P89-R89 -> 1749.5 | T89: =ROUND(S89*Assumptions!$B$2,2) -> 104.97 | U89: =S89+T89 -> 1854.47 | V89: 8.52 | W89: =U89+V89 -> 1862.99 | X89: Backordered | Y89: Reorder of prior PO
A90: South | B90: Texas | C90: Dallas | D90: Granite Outfitters | E90: 41305 | F90: 46222 | G90: 46226 | H90: =IF(G90="","",G90-F90) -> 4 | I90: J. Whitfield | J90: Direct | K90: Safety | L90: Safety Glasses, Clear (12) | M90: SF-0012 | N90: 24 | O90: 27.6 | P90: =N90*O90 -> 662.4 | Q90: 0.05 | R90: =ROUND(P90*Q90,2) -> 33.12 | S90: =P90-R90 -> 629.28 | T90: =ROUND(S90*Assumptions!$B$2,2) -> 37.76 | U90: =S90+T90 -> 667.04 | V90: 43.49 | W90: =U90+V90 -> 710.53 | X90: Delivered | Y90: Reorder of prior PO
A91: South | B91: Texas | C91: Dallas | D91: Granite Outfitters | E91: 41312 | F91: 46081 | G91: 46083 | H91: =IF(G91="","",G91-F91) -> 2 | I91: J. Whitfield | J91: Distributor | K91: Hand Tools | L91: Adjustable Wrench 10 in | M91: HT-1000 | N91: 1 | O91: 19.5 | P91: =N91*O91 -> 19.5 | Q91: 0 | R91: =ROUND(P91*Q91,2) -> 0 | S91: =P91-R91 -> 19.5 | T91: =ROUND(S91*Assumptions!$B$2,2) -> 1.17 | U91: =S91+T91 -> 20.67 | V91: 39.88 | W91: =U91+V91 -> 60.55 | X91: Shipped | Y91: Net 30 terms
A92: South | B92: Texas | C92: Austin | D92: Falcon Hardware | E92: 41313 | F92: 46166 | H92: =IF(G92="","",G92-F92) | I92: J. Whitfield | J92: Online | K92: Fasteners | L92: Hex Bolt 1/2 x 2, Zinc (100) | M92: FAS-1020 | N92: 4 | O92: 18.4 | P92: =N92*O92 -> 73.6 | Q92: 0 | R92: =ROUND(P92*Q92,2) -> 0 | S92: =P92-R92 -> 73.6 | T92: =ROUND(S92*Assumptions!$B$2,2) -> 4.42 | U92: =S92+T92 -> 78.02 | V92: 0 | W92: =U92+V92 -> 78.02 | X92: Open | Y92: Damaged in transit; replaced
A93: South | B93: Texas | C93: Austin | D93: Falcon Hardware | E93: 41320 | F93: 46129 | H93: =IF(G93="","",G93-F93) | I93: J. Whitfield | J93: Direct | K93: Safety | L93: Hard Hat, Type I | M93: SF-0001 | N93: 15 | O93: 21.95 | P93: =N93*O93 -> 329.25 | Q93: 0.05 | R93: =ROUND(P93*Q93,2) -> 16.46 | S93: =P93-R93 -> 312.79 | T93: =ROUND(S93*Assumptions!$B$2,2) -> 18.77 | U93: =S93+T93 -> 331.56 | V93: 33.25 | W93: =U93+V93 -> 364.81 | X93: Backordered | Y93: Damaged in transit; replaced
A94: South | B94: Texas | C94: Austin | D94: Falcon Hardware | E94: 41324 | F94: 46057 | G94: 46059 | H94: =IF(G94="","",G94-F94) -> 2 | I94: J. Whitfield | J94: Distributor | K94: Fasteners | L94: Deck Screw #10 x 3 (5 lb) | M94: FAS-1003 | N94: 6 | O94: 31.9 | P94: =N94*O94 -> 191.4 | Q94: 0 | R94: =ROUND(P94*Q94,2) -> 0 | S94: =P94-R94 -> 191.4 | T94: =ROUND(S94*Assumptions!$B$2,2) -> 11.48 | U94: =S94+T94 -> 202.88 | V94: 14.12 | W94: =U94+V94 -> 217 | X94: Delivered
A95: South | B95: Texas | C95: Austin | D95: Prairie Hardware | E95: 41328 | F95: 46055 | G95: 46058 | H95: =IF(G95="","",G95-F95) -> 3 | I95: J. Whitfield | J95: Direct | K95: Power Tools | L95: Angle Grinder 4-1/2 in | M95: PT-4500 | N95: 5 | O95: 64.5 | P95: =N95*O95 -> 322.5 | Q95: 0.05 | R95: =ROUND(P95*Q95,2) -> 16.13 | S95: =P95-R95 -> 306.37 | T95: =ROUND(S95*Assumptions!$B$2,2) -> 18.38 | U95: =S95+T95 -> 324.75 | V95: 25.47 | W95: =U95+V95 -> 350.22 | X95: Delivered
A96: South | B96: Texas | C96: Austin | D96: Prairie Hardware | E96: 41331 | F96: 46165 | H96: =IF(G96="","",G96-F96) | I96: J. Whitfield | J96: Distributor | K96: Power Tools | L96: Cordless Drill 20V Kit | M96: PT-2001 | N96: 2 | O96: 129 | P96: =N96*O96 -> 258 | Q96: 0 | R96: =ROUND(P96*Q96,2) -> 0 | S96: =P96-R96 -> 258 | T96: =ROUND(S96*Assumptions!$B$2,2) -> 15.48 | U96: =S96+T96 -> 273.48 | V96: 24.1 | W96: =U96+V96 -> 297.58 | X96: Backordered | Y96: New account
A97: South | B97: Texas | C97: Austin | D97: Prairie Hardware | E97: 41336 | F97: 46079 | H97: =IF(G97="","",G97-F97) | I97: J. Whitfield | J97: Direct | K97: Fasteners | L97: Lag Screw 3/8 x 4 (50) | M97: FAS-3804 | N97: 3 | O97: 22.75 | P97: =N97*O97 -> 68.25 | Q97: 0 | R97: =ROUND(P97*Q97,2) -> 0 | S97: =P97-R97 -> 68.25 | T97: =ROUND(S97*Assumptions!$B$2,2) -> 4.1 | U97: =S97+T97 -> 72.35 | V97: 0 | W97: =U97+V97 -> 72.35 | X97: Open
A98: South | B98: Texas | C98: Austin | D98: Northgate Industrial | E98: 41338 | F98: 46050 | G98: 46052 | H98: =IF(G98="","",G98-F98) -> 2 | I98: J. Whitfield | J98: Online | K98: Fasteners | L98: Lag Screw 3/8 x 4 (50) | M98: FAS-3804 | N98: 20 | O98: 22.75 | P98: =N98*O98 -> 455 | Q98: 0.1 | R98: =ROUND(P98*Q98,2) -> 45.5 | S98: =P98-R98 -> 409.5 | T98: =ROUND(S98*Assumptions!$B$2,2) -> 24.57 | U98: =S98+T98 -> 434.07 | V98: 17.98 | W98: =U98+V98 -> 452.05 | X98: Delivered
A99: South | B99: Texas | C99: Austin | D99: Northgate Industrial | E99: 41343 | F99: 46185 | G99: 46190 | H99: =IF(G99="","",G99-F99) -> 5 | I99: S. Nakamura | J99: Online | K99: Safety | L99: Safety Glasses, Clear (12) | M99: SF-0012 | N99: 24 | O99: 27.6 | P99: =N99*O99 -> 662.4 | Q99: 0.05 | R99: =ROUND(P99*Q99,2) -> 33.12 | S99: =P99-R99 -> 629.28 | T99: =ROUND(S99*Assumptions!$B$2,2) -> 37.76 | U99: =S99+T99 -> 667.04 | V99: 19.23 | W99: =U99+V99 -> 686.27 | X99: Delivered
A100: South | B100: Texas | C100: Austin | D100: Northgate Industrial | E100: 41348 | F100: 46083 | G100: 46088 | H100: =IF(G100="","",G100-F100) -> 5 | I100: J. Whitfield | J100: Online | K100: Fasteners | L100: Deck Screw #10 x 3 (5 lb) | M100: FAS-1003 | N100: 1 | O100: 31.9 | P100: =N100*O100 -> 31.9 | Q100: 0 | R100: =ROUND(P100*Q100,2) -> 0 | S100: =P100-R100 -> 31.9 | T100: =ROUND(S100*Assumptions!$B$2,2) -> 1.91 | U100: =S100+T100 -> 33.81 | V100: 35.22 | W100: =U100+V100 -> 69.03 | X100: Delivered | Y100: Partial shipment
...

Sheet Assumptions
A1: Assumption | B1: Value
A2: Sales tax rate | B2: 0.06
A3: Data is fictional and generated for documentation screenshots.
